gender_guesser_br/__init__.py
gender_guesser_br/_ufs.py
gender_guesser_br/errors.py
gender_guesser_br/genero.py
gender_guesser_br-1.1.0.dist-info/LICENSE
gender_guesser_br-1.1.0.dist-info/METADATA
gender_guesser_br-1.1.0.dist-info/WHEEL
gender_guesser_br-1.1.0.dist-info/top_level.txt
gender_guesser_br-1.1.0.dist-info/RECORD
