Metadata-Version: 2.1
Name: gender-guesser-br
Version: 1.1.0
Summary: Versão brasileira do pacote Python para adivinhar o gênero de um nome próprio.
Home-page: https://github.com/GusFurtado/gender_guesser_br
Author: Gustavo Furtado
Author-email: gustavofurtado2@gmail.com
License: MIT
Download-URL: https://github.com/GusFurtado/gender_guesser_br/archive/1.1.0.tar.gz
Keywords: brasil,ibge,dadosabertos,gender,genero
Platform: UNKNOWN
Classifier: Development Status :: 5 - Production/Stable
Classifier: Intended Audience :: Developers
Classifier: Intended Audience :: Science/Research
Classifier: Topic :: Scientific/Engineering
Classifier: License :: OSI Approved :: MIT License
Classifier: Natural Language :: Portuguese (Brazilian)
Classifier: Programming Language :: Python :: 3
Classifier: Programming Language :: Python :: 3.6
Classifier: Programming Language :: Python :: 3.7
Classifier: Programming Language :: Python :: 3.8
Classifier: Programming Language :: Python :: 3.9
Classifier: Programming Language :: Python :: 3.10
Classifier: Programming Language :: Python :: 3.11
Classifier: Programming Language :: Python :: 3.12
Requires-Python: >=3.6
License-File: LICENSE
Requires-Dist: DadosAbertosBrasil >=1.0.0
